constrainedlr/__init__.py
constrainedlr/model.py
constrainedlr/validation.py
constrainedlr-0.2.0.dist-info/LICENCE
constrainedlr-0.2.0.dist-info/METADATA
constrainedlr-0.2.0.dist-info/WHEEL
constrainedlr-0.2.0.dist-info/top_level.txt
constrainedlr-0.2.0.dist-info/RECORD
