Metadata-Version: 2.1
Name: constrainedlr
Version: 0.2.0
Summary: Constrained Linear Regression with sklearn-compatible API
Author-email: Theodore Tsitsimis <th.tsitsimis@gmail.com>
Project-URL: Homepage, https://github.com/tsitsimis/constrainedlr
Classifier: Development Status :: 3 - Alpha
Classifier: Intended Audience :: Developers
Classifier: Intended Audience :: Science/Research
Classifier: License :: OSI Approved :: MIT License
Classifier: Operating System :: OS Independent
Classifier: Programming Language :: Python
Classifier: Programming Language :: Python :: 3
Classifier: Programming Language :: Python :: 3.8
Classifier: Programming Language :: Python :: 3.9
Classifier: Programming Language :: Python :: 3.10
Classifier: Programming Language :: Python :: 3.11
Classifier: Topic :: Scientific/Engineering :: Artificial Intelligence
Classifier: Topic :: Software Development :: Libraries
Requires-Python: >=3.8
License-File: LICENCE
Requires-Dist: numpy >=1.18.0
Requires-Dist: scikit-learn >=1.2.2
Requires-Dist: cvxopt >=1.3.1
Requires-Dist: pandas >=1.2.0
Provides-Extra: dev
Requires-Dist: pytest ; extra == 'dev'
Requires-Dist: jupyter ; extra == 'dev'
Requires-Dist: pre-commit ; extra == 'dev'
Requires-Dist: mypy ; extra == 'dev'
Requires-Dist: coverage ; extra == 'dev'
Requires-Dist: pytest-cov ; extra == 'dev'
Requires-Dist: diff-cover ; extra == 'dev'
Requires-Dist: ruff ; extra == 'dev'
Requires-Dist: build ; extra == 'dev'
